CHANGES.txt
LICENSE.txt
MANIFEST.in
README.txt
setup.py
recordit/__init__.py
recordit/url.py
recordit_url_builder.egg-info/PKG-INFO
recordit_url_builder.egg-info/SOURCES.txt
recordit_url_builder.egg-info/dependency_links.txt
recordit_url_builder.egg-info/top_level.txt