Metadata-Version: 1.0
Name: recordit-url-builder
Version: 1.0.0
Summary: Simple library to generate URLs for recordit API
Home-page: http://pypi.python.org/pypi/recordit-url-builder
Author: Ben Beltran
Author-email: ben@nsovocal.com
License: The MIT License (MIT)
